pylift/__init__.py
pylift/eval.py
pylift/generate_data.py
pylift/style.py
pylift/explore/__init__.py
pylift/explore/base.py
pylift/methods/__init__.py
pylift/methods/base.py
pylift/methods/derivatives.py
pylift-0.1.1.dist-info/DESCRIPTION.rst
pylift-0.1.1.dist-info/METADATA
pylift-0.1.1.dist-info/RECORD
pylift-0.1.1.dist-info/WHEEL
pylift-0.1.1.dist-info/metadata.json
pylift-0.1.1.dist-info/top_level.txt
tests/__init__.py
tests/eval_test.py
tests/methods_test.py
